{"google":"","body":"# Welcome to the Song Classifier !\r\n\r\nThis piece of python code is simple implementation of Python-mutagen.It will help yo classify mp3 songs on the basis of artists and yearwise.\r\n\r\n### How To Use\r\n\r\n1. Install Python-mutagen in your system\r\n2. Run `python songClassifier.py`\r\n\r\n### How to install mutagen \r\n\r\nFor ubuntu users: \r\n\r\n`sudo apt-get install python-mutagen`\r\n\r\nhttps://help.ubuntu.com/community/ConvertingMP3Tags\r\n\r\n## DEMO\r\n1. Install mutagen\r\n2.  Run `python songClassifier.py`\r\n\r\n![Command](http://farm9.staticflickr.com/8046/8093292420_b5b2c3b477.jpg)\r\n\r\nnow you can see output \r\n\r\n![output](http://farm9.staticflickr.com/8472/8093294982_307c464b1b.jpg)","tagline":"classifying mp3 songs ","note":"Don't delete this file! It's used internally to help with page regeneration.","name":"Song Classifier"}